imagine/__init__.py
imagine/async_client.py
imagine/client.py
imagine/client_base.py
imagine/constants.py
imagine/exceptions.py
imagine/logging.py
imagine/py.typed
imagine/utils.py
imagine/langchain/__init__.py
imagine/langchain/chat_models.py
imagine/langchain/embeddings.py
imagine/langchain/llms.py
imagine/langchain/mixins.py
imagine/langchain/py.typed
imagine/types/__init__.py
imagine/types/chat_completions.py
imagine/types/common.py
imagine/types/completions.py
imagine/types/embeddings.py
imagine/types/healthcheck.py
imagine/types/images.py
imagine/types/models.py
imagine/types/reranker.py
imagine/types/transcribe.py
imagine/types/translate.py
imagine/types/usage.py
python_imagine_sdk-0.4.2.dist-info/METADATA
python_imagine_sdk-0.4.2.dist-info/WHEEL
python_imagine_sdk-0.4.2.dist-info/licenses/LICENSE
python_imagine_sdk-0.4.2.dist-info/RECORD
