Metadata-Version: 2.4
Name: python-imagine-sdk
Version: 0.4.2
Summary: A simple Python library for quickly building your own custom AI use case using Qualcomm's inference-as-a-service platform
Project-URL: Cloud AI 100, https://www.qualcomm.com/products/technology/processors/cloud-artificial-intelligence/cloud-ai-100
Project-URL: Qualcomm® Cloud AI SDK, https://github.com/quic/cloud-ai-sdk
Author-email: "Qualcomm Innovation Center, Inc." <quic.opensource@quicinc.com>
Maintainer-email: Sergi Pons Freixes <quic_sponsfre@quicinc.com>, Aditya Parkhi <quic_aparkhi@quicinc.com>, Jayadev Pujari <quic_jpujari@quicinc.com>, Raghava Krishna Yamsani <quic_ryamsani@quicinc.com>
License-Expression: LicenseRef-Proprietary
License-File: LICENSE
Keywords: ai,genai,imagine,llm,qualcomm,quic,sdk
Classifier: Development Status :: 5 - Production/Stable
Classifier: License :: Other/Proprietary License
Classifier: Programming Language :: Python :: 3.9
Classifier: Programming Language :: Python :: 3.10
Classifier: Programming Language :: Python :: 3.11
Classifier: Programming Language :: Python :: 3.12
Classifier: Programming Language :: Python :: 3.13
Requires-Python: >=3.9
Requires-Dist: eval-type-backport; python_version < '3.10'
Requires-Dist: httpx
Requires-Dist: orjson
Requires-Dist: pydantic>=2.0
Requires-Dist: urllib3
Provides-Extra: autogen
Requires-Dist: autogen-agentchat~=0.2; extra == 'autogen'
Provides-Extra: crewai
Requires-Dist: crewai; extra == 'crewai'
Requires-Dist: crewai-tools; extra == 'crewai'
Requires-Dist: litellm; extra == 'crewai'
Provides-Extra: langchain
Requires-Dist: langchain-core>=0.3.0; extra == 'langchain'
